multiauthenticator/__init__.py
multiauthenticator/multiauthenticator.py
jupyterhub_multiauthenticator-0.4.0.dist-info/METADATA
jupyterhub_multiauthenticator-0.4.0.dist-info/WHEEL
jupyterhub_multiauthenticator-0.4.0.dist-info/entry_points.txt
jupyterhub_multiauthenticator-0.4.0.dist-info/top_level.txt
jupyterhub_multiauthenticator-0.4.0.dist-info/RECORD
