Metadata-Version: 2.1
Name: jupyterhub-multiauthenticator
Version: 0.4.0
Summary: Authenticator multiplexer for JupyterHub
Author-email: Samuel Gaist <samuel.gaist@idiap.ch>
License: BSD-3-Clause
Keywords: JupyterHub,Authenticator
Classifier: Intended Audience :: Developers
Classifier: Intended Audience :: System Administrators
Classifier: Intended Audience :: Science/Research
Classifier: License :: OSI Approved :: BSD License
Classifier: Programming Language :: Python
Classifier: Programming Language :: Python :: 3
Requires-Dist: jupyterhub
Requires-Dist: importlib-metadata >=4.6 ; python_version < "3.10"
Provides-Extra: dev
Requires-Dist: pre-commit ; extra == 'dev'
Requires-Dist: jupyterhub-multiauthenticator[test] ; extra == 'dev'
Provides-Extra: test
Requires-Dist: pytest ; extra == 'test'
Requires-Dist: pytest-cov ; extra == 'test'
Requires-Dist: pytest-asyncio ; extra == 'test'
Requires-Dist: oauthenticator ; extra == 'test'
